mysqlwrapper/__init__.py
mysqlwrapper/connection.py
mysqlwrapper/decorators.py
mysqlwrapper-0.1.1.dist-info/licenses/LICENSE
mysqlwrapper-0.1.1.dist-info/METADATA
mysqlwrapper-0.1.1.dist-info/WHEEL
mysqlwrapper-0.1.1.dist-info/top_level.txt
mysqlwrapper-0.1.1.dist-info/RECORD
