Metadata-Version: 2.4
Name: mysqlwrapper
Version: 0.1.1
Summary: A lightweight wrapper for PyMySQL with auto-cursor decorators
Author-email: Ventros <ventros.development@gmail.com>
License: MIT
Requires-Python: >=3.10
License-File: LICENSE
Requires-Dist: pymysql
Dynamic: license-file
